RedXSecurePayments/__init__.py
RedXSecurePayments/core.py
RedXSecurePayments-1.1.2.dist-info/METADATA
RedXSecurePayments-1.1.2.dist-info/WHEEL
RedXSecurePayments-1.1.2.dist-info/top_level.txt
RedXSecurePayments-1.1.2.dist-info/RECORD
