Metadata-Version: 2.2
Name: RedXSecurePayments
Version: 1.1.2
Summary: A flexible and secure payment collection system using Stripe
Home-page: https://pypi.org/project/RedXSecurePayments/
Author: RedX
Author-email: RedX <RedXDevelopment1998@gmail.com>
License: MIT
Project-URL: Homepage, https://pypi.org/project/RedXSecurePayments/
Project-URL: Repository, https://github.com/RedXSecurePayments/RedXSecurePayments
Requires-Python: >=3.7
Requires-Dist: stripe>=7.0.0
Requires-Dist: flask>=2.0.0
Requires-Dist: setuptools>=68.0.0
Requires-Dist: build>=1.1.1
Requires-Dist: twine>=4.0.2
Dynamic: author
Dynamic: home-page
Dynamic: requires-python
